{
  "collapse-filter": false,
  "search": "-path: \"node_modules\"  -path:00_Templates  ",
  "showTags": true,
  "showAttachments": false,
  "hideUnresolved": true,
  "showOrphans": true,
  "collapse-color-groups": true,
  "colorGroups": [
    {
      "query": "file:___",
      "color": {
        "a": 1,
        "rgb": 16711680
      }
    },
    {
      "query": "file:__",
      "color": {
        "a": 1,
        "rgb": 16761512
      }
    },
    {
      "query": "file:_",
      "color": {
        "a": 1,
        "rgb": 1690652
      }
    },
    {
      "query": "path:\"01_Conocimiento\" ",
      "color": {
        "a": 1,
        "rgb": 10027008
      }
    },
    {
      "query": "path:02_Proyectos  ",
      "color": {
        "a": 1,
        "rgb": 16734464
      }
    },
    {
      "query": "path:03_Youtube  ",
      "color": {
        "a": 1,
        "rgb": 5431378
      }
    },
    {
      "query": "path:04_CarnetConducir  ",
      "color": {
        "a": 1,
        "rgb": 5431473
      }
    },
    {
      "query": "path:00_Templates  ",
      "color": {
        "a": 1,
        "rgb": 14701138
      }
    },
    {
      "query": "path:10_Diary  ",
      "color": {
        "a": 1,
        "rgb": 5395168
      }
    }
  ],
  "collapse-display": true,
  "showArrow": true,
  "textFadeMultiplier": -2.9,
  "nodeSizeMultiplier": 1.01875,
  "lineSizeMultiplier": 2.67760416666667,
  "collapse-forces": false,
  "centerStrength": 0.03125,
  "repelStrength": 6.66666666666667,
  "linkStrength": 0.604166666666667,
  "linkDistance": 64,
  "scale": 0.34613323592870937,
  "close": true
}